hallmonitor/__init__.py
hallmonitor/addons.py
hallmonitor/api.py
hallmonitor/hallmonitor.py
hallmonitor/wsgi.py
hallmonitor/resources/__init__.py
hallmonitor/resources/endpoint.py
hallmonitor/resources/health.py
hallmonitor/services/__init__.py
hallmonitor/services/endpoint.py
hallmonitor-0.6.3.data/scripts/hallmonitor
hallmonitor-0.6.3.dist-info/METADATA
hallmonitor-0.6.3.dist-info/WHEEL
hallmonitor-0.6.3.dist-info/pbr.json
hallmonitor-0.6.3.dist-info/top_level.txt
hallmonitor-0.6.3.dist-info/RECORD
